wt_ts_filler/Filling_gaps.py
wt_ts_filler/__init__.py
wt_ts_filler/cleaning.py
wt_ts_filler/plotting.py
wt_ts_filler-0.1.0.dist-info/METADATA
wt_ts_filler-0.1.0.dist-info/WHEEL
wt_ts_filler-0.1.0.dist-info/RECORD
