Metadata-Version: 2.4
Name: wt_ts_filler
Version: 0.1.0
Summary: Cleaner and filler of groundwater level time series, using correlated time series from neighboring wells
Project-URL: Homepage, https://github.com/FannyPicou/wt_ts_filler
Project-URL: Bug Tracker, https://github.com/FannyPicou/wt_ts_filler/issues
Author-email: Fanny Picourlat <fanny.picourlat@gmail.com>
Classifier: Development Status :: 2 - Pre-Alpha
Classifier: License :: OSI Approved :: MIT License
Classifier: Operating System :: OS Independent
Classifier: Programming Language :: Python :: 3
Classifier: Topic :: Scientific/Engineering
Requires-Python: >=3.8
Requires-Dist: matplotlib
Requires-Dist: numpy
Requires-Dist: pandas
Requires-Dist: scipy
Provides-Extra: dev
Requires-Dist: black; extra == 'dev'
Requires-Dist: mkdocs; extra == 'dev'
Requires-Dist: mkdocs-material; extra == 'dev'
Requires-Dist: mkdocstrings[python]; extra == 'dev'
Requires-Dist: pytest; extra == 'dev'
Requires-Dist: ruff; extra == 'dev'
Provides-Extra: test
Requires-Dist: pytest; extra == 'test'
